meatgen/__init__.py
meatgen/cli.py
meatgen/generate.py
meatgen-0.1.3.dist-info/METADATA
meatgen-0.1.3.dist-info/WHEEL
meatgen-0.1.3.dist-info/entry_points.txt
meatgen-0.1.3.dist-info/top_level.txt
meatgen-0.1.3.dist-info/RECORD
