Metadata-Version: 2.1
Name: meatgen
Version: 0.1.3
Summary: Generate passwords via real world phenomena
Home-page: http://github.com/buckley-w-david/Meatspace-password-generator
Author: David Buckley
Author-email: buckley.w.david@gmail.com
License: UNLICENSE
Platform: UNKNOWN
Classifier: Development Status :: 3 - Alpha
Classifier: License :: OSI Approved :: MIT License
Classifier: Programming Language :: Python :: 3.6
